{
                         "08:00": [
                                                  true,
                                                  null
                         ],
                         "08:30": [
                                                  false,
                                                  {
                                                                           "name": "Anna",
                                                                           "surname": "Pfeifer",
                                                                           "pesel": "94426763753"
                                                  }
                         ],
                         "09:00": [
                                                  false,
                                                  {
                                                                           "name": "Johnny",
                                                                           "surname": "Teal",
                                                                           "pesel": "85978974222"
                                                  }
                         ],
                         "09:30": [
                                                  true,
                                                  null
                         ],
                         "10:00": [
                                                  true,
                                                  null
                         ],
                         "10:30": [
                                                  false,
                                                  {
                                                                           "name": "Mark",
                                                                           "surname": "Hamel",
                                                                           "pesel": "23654392646"
                                                  }
                         ],
                         "11:00": [
                                                  true,
                                                  null
                         ],
                         "11:30": [
                                                  true,
                                                  null
                         ],
                         "12:00": [
                                                  true,
                                                  null
                         ],
                         "12:30": [
                                                  true,
                                                  null
                         ],
                         "13:00": [
                                                  false,
                                                  {
                                                                           "name": "Erin",
                                                                           "surname": "Baird",
                                                                           "pesel": "04661478432"
                                                  }
                         ],
                         "13:30": [
                                                  true,
                                                  null
                         ],
                         "14:00": [
                                                  true,
                                                  null
                         ],
                         "14:30": [
                                                  true,
                                                  null
                         ],
                         "15:00": [
                                                  true,
                                                  null
                         ],
                         "15:30": [
                                                  false,
                                                  {
                                                                           "name": "Terence",
                                                                           "surname": "Garcia",
                                                                           "pesel": "28800542607"
                                                  }
                         ],
                         "16:00": [
                                                  true,
                                                  null
                         ],
                         "16:30": [
                                                  false,
                                                  {
                                                                           "name": "Laurie",
                                                                           "surname": "Toman",
                                                                           "pesel": "36322601709"
                                                  }
                         ],
                         "17:00": [
                                                  false,
                                                  {
                                                                           "name": "Kathleen",
                                                                           "surname": "Page",
                                                                           "pesel": "88031996295"
                                                  }
                         ],
                         "17:30": [
                                                  true,
                                                  null
                         ],
                         "18:00": [
                                                  false,
                                                  {
                                                                           "name": "Margaret",
                                                                           "surname": "Brady",
                                                                           "pesel": "41331896214"
                                                  }
                         ],
                         "18:30": [
                                                  false,
                                                  {
                                                                           "name": "Blanche",
                                                                           "surname": "Elliott",
                                                                           "pesel": "47731387770"
                                                  }
                         ],
                         "19:00": [
                                                  false,
                                                  {
                                                                           "name": "Brandon",
                                                                           "surname": "Miller",
                                                                           "pesel": "51890201902"
                                                  }
                         ],
                         "19:30": [
                                                  true,
                                                  null
                         ],
                         "20:00": [
                                                  true,
                                                  null
                         ]
}