{
                         "08:00": [
                                                  true,
                                                  null
                         ],
                         "08:30": [
                                                  true,
                                                  null
                         ],
                         "09:00": [
                                                  true,
                                                  null
                         ],
                         "09:30": [
                                                  false,
                                                  {
                                                                           "name": "Justin",
                                                                           "surname": "Mingle",
                                                                           "pesel": "57292711396"
                                                  }
                         ],
                         "10:00": [
                                                  true,
                                                  null
                         ],
                         "10:30": [
                                                  false,
                                                  {
                                                                           "name": "Joseph",
                                                                           "surname": "Gerry",
                                                                           "pesel": "53141977904"
                                                  }
                         ],
                         "11:00": [
                                                  true,
                                                  null
                         ],
                         "11:30": [
                                                  true,
                                                  null
                         ],
                         "12:00": [
                                                  false,
                                                  {
                                                                           "name": "Gregory",
                                                                           "surname": "Casey",
                                                                           "pesel": "45325537565"
                                                  }
                         ],
                         "12:30": [
                                                  false,
                                                  {
                                                                           "name": "Amber",
                                                                           "surname": "Dessert",
                                                                           "pesel": "92724030798"
                                                  }
                         ],
                         "13:00": [
                                                  true,
                                                  null
                         ],
                         "13:30": [
                                                  true,
                                                  null
                         ],
                         "14:00": [
                                                  false,
                                                  {
                                                                           "name": "Martin",
                                                                           "surname": "Mitchell",
                                                                           "pesel": "18066889081"
                                                  }
                         ],
                         "14:30": [
                                                  false,
                                                  {
                                                                           "name": "Margie",
                                                                           "surname": "Sanders",
                                                                           "pesel": "44348378876"
                                                  }
                         ],
                         "15:00": [
                                                  false,
                                                  {
                                                                           "name": "Jaclyn",
                                                                           "surname": "Hall",
                                                                           "pesel": "16147237120"
                                                  }
                         ],
                         "15:30": [
                                                  false,
                                                  {
                                                                           "name": "Jennifer",
                                                                           "surname": "Merida",
                                                                           "pesel": "74262212955"
                                                  }
                         ],
                         "16:00": [
                                                  true,
                                                  null
                         ],
                         "16:30": [
                                                  false,
                                                  {
                                                                           "name": "Nellie",
                                                                           "surname": "Bernacchi",
                                                                           "pesel": "15825564656"
                                                  }
                         ],
                         "17:00": [
                                                  true,
                                                  null
                         ],
                         "17:30": [
                                                  true,
                                                  null
                         ],
                         "18:00": [
                                                  false,
                                                  {
                                                                           "name": "Kaitlyn",
                                                                           "surname": "Smith",
                                                                           "pesel": "60072922278"
                                                  }
                         ],
                         "18:30": [
                                                  false,
                                                  {
                                                                           "name": "Rebecca",
                                                                           "surname": "Hendricks",
                                                                           "pesel": "12352453040"
                                                  }
                         ],
                         "19:00": [
                                                  true,
                                                  null
                         ],
                         "19:30": [
                                                  false,
                                                  {
                                                                           "name": "John",
                                                                           "surname": "Girven",
                                                                           "pesel": "55132836550"
                                                  }
                         ],
                         "20:00": [
                                                  true,
                                                  null
                         ]
}