{
                         "08:00": [
                                                  false,
                                                  {
                                                                           "name": "Henry",
                                                                           "surname": "Bundren",
                                                                           "pesel": "96749009739"
                                                  }
                         ],
                         "08:30": [
                                                  false,
                                                  {
                                                                           "name": "Rachael",
                                                                           "surname": "Molina",
                                                                           "pesel": "08412960784"
                                                  }
                         ],
                         "09:00": [
                                                  true,
                                                  null
                         ],
                         "09:30": [
                                                  false,
                                                  {
                                                                           "name": "Molly",
                                                                           "surname": "Highfill",
                                                                           "pesel": "59960031890"
                                                  }
                         ],
                         "10:00": [
                                                  false,
                                                  {
                                                                           "name": "Gregory",
                                                                           "surname": "Davis",
                                                                           "pesel": "16015419563"
                                                  }
                         ],
                         "10:30": [
                                                  false,
                                                  {
                                                                           "name": "Jonathan",
                                                                           "surname": "Hildreth",
                                                                           "pesel": "94882565361"
                                                  }
                         ],
                         "11:00": [
                                                  false,
                                                  {
                                                                           "name": "Dennis",
                                                                           "surname": "Espinoza",
                                                                           "pesel": "72600968752"
                                                  }
                         ],
                         "11:30": [
                                                  true,
                                                  null
                         ],
                         "12:00": [
                                                  false,
                                                  {
                                                                           "name": "Margaret",
                                                                           "surname": "Young",
                                                                           "pesel": "56589899594"
                                                  }
                         ],
                         "12:30": [
                                                  false,
                                                  {
                                                                           "name": "James",
                                                                           "surname": "Mcnabb",
                                                                           "pesel": "75747011292"
                                                  }
                         ],
                         "13:00": [
                                                  true,
                                                  null
                         ],
                         "13:30": [
                                                  false,
                                                  {
                                                                           "name": "Tawana",
                                                                           "surname": "Jeffers",
                                                                           "pesel": "37795703965"
                                                  }
                         ],
                         "14:00": [
                                                  true,
                                                  null
                         ],
                         "14:30": [
                                                  true,
                                                  null
                         ],
                         "15:00": [
                                                  true,
                                                  null
                         ],
                         "15:30": [
                                                  false,
                                                  {
                                                                           "name": "Michael",
                                                                           "surname": "Bean",
                                                                           "pesel": "72329451400"
                                                  }
                         ],
                         "16:00": [
                                                  false,
                                                  {
                                                                           "name": "Lorraine",
                                                                           "surname": "Arnold",
                                                                           "pesel": "74497658634"
                                                  }
                         ],
                         "16:30": [
                                                  true,
                                                  null
                         ],
                         "17:00": [
                                                  true,
                                                  null
                         ],
                         "17:30": [
                                                  false,
                                                  {
                                                                           "name": "Patricia",
                                                                           "surname": "Griffith",
                                                                           "pesel": "75120969702"
                                                  }
                         ],
                         "18:00": [
                                                  true,
                                                  null
                         ],
                         "18:30": [
                                                  true,
                                                  null
                         ],
                         "19:00": [
                                                  true,
                                                  null
                         ],
                         "19:30": [
                                                  false,
                                                  {
                                                                           "name": "Nathan",
                                                                           "surname": "Reed",
                                                                           "pesel": "45081753547"
                                                  }
                         ],
                         "20:00": [
                                                  false,
                                                  {
                                                                           "name": "Alfred",
                                                                           "surname": "Nava",
                                                                           "pesel": "96235981328"
                                                  }
                         ]
}